pydoku/__init__.py
pydoku/board.py
pydoku/test_board.py
pydoku-0.1.1.dist-info/LICENSE
pydoku-0.1.1.dist-info/METADATA
pydoku-0.1.1.dist-info/WHEEL
pydoku-0.1.1.dist-info/top_level.txt
pydoku-0.1.1.dist-info/zip-safe
pydoku-0.1.1.dist-info/RECORD
