Metadata-Version: 2.1
Name: pydoku
Version: 0.1.1
Summary: A python implementation of a Sudoku solver.
Home-page: https://github.com/marstr/pydoku
Author: marstr
Author-email: martin.strobel@live.com
License: MIT
Platform: UNKNOWN
